wolensing/__about__.py
wolensing/amplification_factor/__init__.py
wolensing/amplification_factor/amplification_factor.py
wolensing/lensmodels/__init__.py
wolensing/lensmodels/derivative.py
wolensing/lensmodels/hessian.py
wolensing/lensmodels/lens.py
wolensing/lensmodels/potential.py
wolensing/plot/__init__.py
wolensing/plot/plot.py
wolensing/utils/__init__.py
wolensing/utils/constants.py
wolensing/utils/histogram.py
wolensing/utils/utils.py
wolensing-0.0.10.dist-info/METADATA
wolensing-0.0.10.dist-info/WHEEL
wolensing-0.0.10.dist-info/licenses/LICENSE
wolensing-0.0.10.dist-info/RECORD
