Metadata-Version: 2.3
Name: wolensing
Version: 0.0.10
Summary: A package for computing wave optics amplification factor.
Project-URL: Homepage, https://github.com/manchunyeung/wolensing
Author-email: "Simon Man-Chun Yeung, Mark Ho-Yeuk Cheung" <yeungm@uwm.edu>
License-File: LICENSE
Classifier: License :: OSI Approved :: MIT License
Classifier: Operating System :: OS Independent
Classifier: Programming Language :: Python :: 3.9
Classifier: Programming Language :: Python :: 3.10
Classifier: Programming Language :: Python :: 3.11
Requires-Python: <3.12,>=3.9
Requires-Dist: extension-helpers
Requires-Dist: fast-histogram
Requires-Dist: jax>=0.4.27
Requires-Dist: jaxlib
Requires-Dist: lenstronomy
Requires-Dist: matplotlib
Requires-Dist: mpmath
Requires-Dist: numba==0.59.0
Requires-Dist: numpy>=1.21
Requires-Dist: pycbc
Requires-Dist: scipy>1.4.1
Requires-Dist: tqdm
